mVarScan/__init__.py
mVarScan/__main__.py
mVarScan/cli.py
mVarScan/main.py
mVarScan/mpileup_parser.py
mVarScan/variant_caller.py
mVarScan-0.1.10.dist-info/METADATA
mVarScan-0.1.10.dist-info/WHEEL
mVarScan-0.1.10.dist-info/entry_points.txt
mVarScan-0.1.10.dist-info/top_level.txt
mVarScan-0.1.10.dist-info/RECORD
