Metadata-Version: 2.1
Name: mVarScan
Version: 0.1.10
Summary: An implementation of the existing VarScan tool (specifically mpileup2snp option). Used to find SNPs given a .mpileup file
Home-page: https://github.com/andrewbigelow/mVarScan/tree/main
Author: Andrew Bigelow, Numaan Formoli, Aditya Parmar
Author-email: abigelow@ucsd.edu
License: Proprietary
Classifier: Development Status :: 1 - Planning
Classifier: Intended Audience :: Science/Research
Classifier: License :: Other/Proprietary License
Classifier: Operating System :: POSIX :: Linux
Classifier: Programming Language :: Python :: 3
Classifier: Programming Language :: Python :: 3.6
Classifier: Programming Language :: Python :: 3.7
Classifier: Programming Language :: Python :: 3.8
Classifier: Programming Language :: Python :: 3.9
Requires-Python: >=3.6
Requires-Dist: mpi4py >=3.0
Requires-Dist: scipy
